__init__.py
file_manager.py
filecleaner-0.1.1.dist-info/LICENSE
filecleaner-0.1.1.dist-info/METADATA
filecleaner-0.1.1.dist-info/WHEEL
filecleaner-0.1.1.dist-info/entry_points.txt
filecleaner-0.1.1.dist-info/top_level.txt
filecleaner-0.1.1.dist-info/RECORD
