Metadata-Version: 2.1
Name: filecleaner
Version: 0.1.1
Summary: A simple command line utility that organises files in a directory into subdirectories.
Home-page: https://github.com/timnw2000/File-Manager
Author: Tim Nwungang
Author-email: timnw.dev@gmail.com
Maintainer-email: timnw.dev@gmail.com
License: MIT
Project-URL: Documentation, https://github.com/timnw2000/File-Manager/blob/creating_gui/README.md
Requires: setuptools
License-File: LICENSE
Requires-Dist: appdirs ==1.4.4
Requires-Dist: blessed ==1.20.0
Requires-Dist: flyingcircus ==0.1.4.1
Requires-Dist: packaging ==23.2
Requires-Dist: pytk ==0.0.2.1
Requires-Dist: six ==1.16.0
Requires-Dist: typing-extensions ==4.8.0
Requires-Dist: wcwidth ==0.2.12
